get_pwbrowser/__init__.py
get_pwbrowser/config.py
get_pwbrowser/get_pwbrowser.py
get_pwbrowser/get_pwbrowser_async.py
get_pwbrowser-0.1.1.dist-info/WHEEL
get_pwbrowser-0.1.1.dist-info/METADATA
get_pwbrowser-0.1.1.dist-info/RECORD
